pyctp_zp/__init__.py
pyctp_zp/CPPyCTP/__init__.py
pyctp_zp/CPPyCTP/_thostmduserapi.pyd
pyctp_zp/CPPyCTP/_thosttraderapi.pyd
pyctp_zp/CPPyCTP/thostmduserapi.py
pyctp_zp/CPPyCTP/thostmduserapi_se.dll
pyctp_zp/CPPyCTP/thosttraderapi.py
pyctp_zp/CPPyCTP/thosttraderapi_se.dll
pyctp_zp/PyCTP/__init__.py
pyctp_zp/PyCTP/_thostmduserapi.pyd
pyctp_zp/PyCTP/_thosttraderapi.pyd
pyctp_zp/PyCTP/thostmduserapi.py
pyctp_zp/PyCTP/thostmduserapi_se.dll
pyctp_zp/PyCTP/thosttraderapi.py
pyctp_zp/PyCTP/thosttraderapi_se.dll
pyctp_zp-6.7.9.1.dist-info/METADATA
pyctp_zp-6.7.9.1.dist-info/WHEEL
pyctp_zp-6.7.9.1.dist-info/top_level.txt
pyctp_zp-6.7.9.1.dist-info/RECORD
