Metadata-Version: 2.4
Name: pyctp-zp
Version: 6.7.9.1
Summary: CTP Python接口，支持行情和交易，兼容PyCTP和CPPyCTP
Home-page: https://pypi.org/project/pyctp-zp/
Author: luochenyeling
Author-email: zhaokehan86@163.com
Classifier: Programming Language :: Python :: 3
Classifier: Operating System :: Microsoft :: Windows
Requires-Python: >=3.7
Dynamic: author
Dynamic: author-email
Dynamic: classifier
Dynamic: description
Dynamic: description-content-type
Dynamic: home-page
Dynamic: requires-python
Dynamic: summary
